vaspirin/__init__.py
vaspirin/datIO.py
vaspirin/doscar.py
vaspirin/graceIO.py
vaspirin/outcar.py
vaspirin/poscar.py
vaspirin/procar.py
vaspirin/projection.py
vaspirin/splitter.py
vaspirin-2.0.data/scripts/band_offsets.py
vaspirin-2.0.data/scripts/colored_bands.py
vaspirin-2.0.data/scripts/dos.py
vaspirin-2.0.data/scripts/gen_kpoints.py
vaspirin-2.0.data/scripts/move_atoms.py
vaspirin-2.0.data/scripts/plot_bands.py
vaspirin-2.0.data/scripts/plot_compared_bands.py
vaspirin-2.0.data/scripts/rotate_molecule.py
vaspirin-2.0.data/scripts/split_procar.py
vaspirin-2.0.data/scripts/strain_cell.py
vaspirin-2.0.dist-info/LICENSE
vaspirin-2.0.dist-info/METADATA
vaspirin-2.0.dist-info/WHEEL
vaspirin-2.0.dist-info/top_level.txt
vaspirin-2.0.dist-info/RECORD
