Metadata-Version: 2.1
Name: vaspirin
Version: 2.0
Summary: Painless VASP post-processing tool
Home-page: http://www.gmsn.ita.br/
Author: Daniel S. Koda, Ivan Guilhon
Author-email: danielskoda@gmail.com, ivanguilhonn@gmail.com 
License: UNKNOWN
Download-URL: https://github.com/gmsn-ita/vaspirin
Platform: UNKNOWN
Requires: matplotlib
Requires: numpy
Requires: scipy
Requires: pylab
Requires: itertools
